bmb_klondike_client/__init__.py
bmb_klondike_client/api_client.py
bmb_klondike_client/configuration.py
bmb_klondike_client/rest.py
bmb_klondike_client/api/__init__.py
bmb_klondike_client/api/claims_api.py
bmb_klondike_client/api/unaddressed_messages_api.py
bmb_klondike_client/models/__init__.py
bmb_klondike_client/models/claim.py
bmb_klondike_client/models/claim_response.py
bmb_klondike_client/models/selection_metadata.py
bmb_klondike_client/models/unaddressed_message.py
bmb_klondike_client/models/unaddressed_message_response.py
bmb_klondike_client/models/unaddressed_messages_response.py
test/__init__.py
test/test_claim.py
test/test_claim_response.py
test/test_claims_api.py
test/test_selection_metadata.py
test/test_unaddressed_message.py
test/test_unaddressed_message_response.py
test/test_unaddressed_messages_api.py
test/test_unaddressed_messages_response.py
bmb_klondike_client-0.3.0.dist-info/METADATA
bmb_klondike_client-0.3.0.dist-info/WHEEL
bmb_klondike_client-0.3.0.dist-info/top_level.txt
bmb_klondike_client-0.3.0.dist-info/RECORD
