Metadata-Version: 2.1
Name: bmb-klondike-client
Version: 0.3.0
Summary: Klondike API
Home-page: UNKNOWN
Author: UNKNOWN
Author-email: apiteam@bmbix.com
License: UNKNOWN
Keywords: Swagger,Klondike API
Platform: UNKNOWN
Requires-Dist: certifi
Requires-Dist: python-dateutil
Requires-Dist: six (>=1.10)
Requires-Dist: urllib3 (>=1.15)
